{"inkVersion":21,"root":[["^Oh ho ho, schon wieder zurück? Sie konnten sich einfach nicht von meinen fabelhaften Waren verabschieben, was? ","#","^speaker: oswald ","/#","#","^emotion: NERVOUS","/#","\n",{"->":"Topics"},["done",{"#f":5,"#n":"g-0"}],null],"done",{"Topics":[["ev","str","^Dieses Amulett...","/str","/ev",{"*":".^.c-0","flg":4},"ev","str","^Der Dieb","/str","/ev",{"*":".^.c-1","flg":4},"ev","str","^Tschüss","/str","/ev",{"*":".^.c-2","flg":4},{"c-0":["^ ",{"->":"Amulett"},"\n",{"#f":5}],"c-1":["^ ",{"->":"Dieb"},"\n",{"#f":5}],"c-2":["^ ",{"->":"Bye"},"\n",{"#f":5}]}],{"#f":1}],"Amulett":[{"->":"Topics"},{"#f":1}],"Dieb":[{"->":"Topics"},{"#f":1}],"Bye":["^Auf Wiedersehen. ","#","^speaker: marcus ","/#","#","^emotion: NORMAL","/#","\n","^Kommen Sie bald wieder! ","#","^speaker: oswald ","/#","#","^emotion: NORMAL","/#","\n","end",{"#f":1}],"#f":1}],"listDefs":{}}