{"inkVersion":21,"root":[["^Hallo? Ist hier jemand? ","#","^speaker:marcus ","/#","#","^emotion:NORMAL","/#","\n","^Hier drüben, junger Mann. ","#","^speaker:oswald ","/#","#","^emotion:NORMAL","/#","\n","^... ","#","^pause: Marcus geht zu oswald","/#","\n","^Ich bin wegen des Amulettes hier. ","#","^speaker:marcus ","/#","#","^emotion:NORMAL","/#","\n","^Oh, stimmt. Dann musst du der Marcus Clark sein?[nl]Der Geschichtsprofessor aus dieser renomierten Universität...wie war der Name nochmal? ","#","^speaker:oswald ","/#","#","^emotion:NORMAL","/#","\n","^Die Westmond Universität. ","#","^speaker:marcus ","/#","#","^emotion:NORMAL","/#","\n","^Oh ja, richtig! ","#","^speaker:oswald ","/#","#","^emotion:NORMAL","/#","\n","^...  ","#","^speaker:marcus ","/#","#","^emotion:NORMAL","/#","\n","^... ","#","^speaker:oswald ","/#","#","^emotion:NERVOUS","/#","\n","^Was ist nun mit dem Amulett? ","#","^speaker:marcus ","/#","#","^emotion:NORMAL","/#","\n","^Ach ja, das Schmuckstück, von dem man sich nachsagt, es habe magische Kräfte![nl]Für jeden Sammler ein Must-Have!","#","^speaker:oswald ","/#","#","^emotion:NORMAL","/#","\n","^Es gibt aber keine Rückgabegarantie! ","#","^speaker:oswald ","/#","#","^emotion:HAPPY","/#","\n","^Sparen Sie mir bitte die Details. Wo ist es? ","#","^speaker:marcus ","/#","#","^emotion:NORMAL","/#","\n","^...","#","^speaker:oswald ","/#","#","^emotion:NERVOUS","/#","\n","^Hier bitteschön...","#","^speaker:oswald ","/#","#","^emotion:NERVOUS","/#","\n","^... ","#","^pause: Marcus kickt gegen den Tisch und Oswald erschrickt sich","/#","\n","^Wollen Sie mich veralbern? Da fehlt ja die Hälfte! ","#","^speaker:marcus ","/#","#","^emotion:ANGRY","/#","\n","^Nun, schauen Sie mich doch nicht so dämonisch an, sonst verscheuchen Sie noch alle guten Geister!","#","^speaker:oswald ","/#","#","^emotion:NERVOUS","/#","\n","^Falls Sie wollen, gebe ich Ihnen noch als Bonus dieses andere Schmuckstück kostenlos mit. Das ist doch ein Schnapper, oder?","#","^speaker:oswald ","/#","#","^emotion:HAPPY","/#","\n","^... ","#","^speaker:marcus ","/#","#","^emotion:ANGRY","/#","\n","^Okay, ich verstehe.","#","^speaker:oswald ","/#","#","^emotion:NERVOUS","/#","\n","^Wissen Sie, die Sache ist die... Ich, alter Mann, wachte an einem friedlichen Freitagmorgen auf... ","#","^speaker:oswald ","/#","#","^emotion:NERVOUS","/#","\n","^Es war Freitag, der Dreizehnte. Damit hatte das Schicksal also bereits bestimmt, dass ich vom Pech verfolgt werden würde- ","#","^speaker:oswald ","/#","#","^emotion:NERVOUS","/#","\n","^Du hast sie verloren? ","#","^speaker:marcus ","/#","#","^emotion:ANGRY","/#","\n","^Verloren ist der falsche Begriff! Es wurde mir gestohlen! Ich habe ihn auf frischer Tat ertappt... ","#","^speaker:oswald ","/#","#","^emotion:NERVOUS","/#","\n","^... Nur leider konnte ich ihn nur teilweise aufhalten.","#","^speaker:oswald ","/#","#","^emotion:NERVOUS","/#","\n","^... ","#","^speaker:marcus ","/#","#","^emotion:NORMAL","/#","\n","^Und deshalb ist Ihre Ware auch in diesem Zustand, mein Herr. Ich verfluche diesen Dieb! ","#","^speaker:oswald ","/#","#","^emotion:NORMAL","/#","\n","^*Seufz*.[nl]Dann nehm ich halt nur die Hälfte...","#","^speaker:marcus ","/#","#","^emotion:NORMAL","/#","\n","^Das freut mich. Das macht dann 3000 Dollar! ","#","^speaker:oswald ","/#","#","^emotion:HAPPY","/#","\n","^... ","#","^speaker:marcus ","/#","#","^emotion:ANGRY","/#","\n","^3-300! Ich meinte natürlich 300 Dollar. Das war nur ein Scherz! Nur ein kleiner Insider zwischen Sammlern! ","#","^speaker:oswald ","/#","#","^emotion:NERVOUS","/#","\n","^Oswald reicht Marcus ein Amulett, während Marcus ihm 300 Dollar gibt.","#","^speaker:narrator","/#","\n","^Das Amulett liegt kühl in seiner Hand. Er steckt es in seine Tasche.","#","^speaker:narrator","/#","\n","^Es war mir eine Freude, mit dir Geschäfte zu machen! Bis zum nächsten Mal! ","#","^speaker:oswald ","/#","#","^emotion:HAPPY","/#","\n","^Auf Wiedersehen.","#","^speaker:marcus ","/#","#","^emotion:NORMAL","/#","\n","^... ","#","^pause: Marcus verlässt den Laden","/#","\n","^(Es ist schon Mittagszeit. Ich sollte mir etwas zu Essen besorgen.) ","#","^speaker:marcus ","/#","#","^emotion:NERVOUS","/#","\n","end",["done",{"#f":5,"#n":"g-0"}],null],"done",{"#f":1}],"listDefs":{}}